sopel_dns/__init__.py
sopel_dns/plugin.py
sopel_dns-0.5.0.dist-info/COPYING
sopel_dns-0.5.0.dist-info/METADATA
sopel_dns-0.5.0.dist-info/WHEEL
sopel_dns-0.5.0.dist-info/entry_points.txt
sopel_dns-0.5.0.dist-info/top_level.txt
sopel_dns-0.5.0.dist-info/RECORD
