Metadata-Version: 2.1
Name: sopel-dns
Version: 0.5.0
Summary: A DNS lookup plugin for Sopel IRC bots
Author-email: dgw <dgw@technobabbl.es>
License: EFL-2.0
Project-URL: Homepage, https://github.com/dgw/sopel-dns
Project-URL: Bug Tracker, https://github.com/dgw/sopel-dns/issues
Keywords: sopel,plugin,bot,irc
Platform: Linux x86, x86-64
Classifier: Intended Audience :: Developers
Classifier: Intended Audience :: System Administrators
Classifier: License :: Eiffel Forum License (EFL)
Classifier: License :: OSI Approved :: Eiffel Forum License
Classifier: Topic :: Communications :: Chat :: Internet Relay Chat
Classifier: Programming Language :: Python :: 3 :: Only
Classifier: Programming Language :: Python :: 3.8
Classifier: Programming Language :: Python :: 3.9
Classifier: Programming Language :: Python :: 3.10
Classifier: Programming Language :: Python :: 3.11
Classifier: Programming Language :: Python :: 3.12
Requires-Python: <4,>=3.8
License-File: COPYING
Requires-Dist: sopel>=8.0
Requires-Dist: dnspython<3,>=2.0
